[
    { "driver": "Fadel", "team": "Shinano Pertamina Team", "points": 157 },
    { "driver": "Dappa", "team": "South Ranger Subaru", "points": 149 },
    { "driver": "Tada", "team": "Redbull Audi Sport", "points": 144 },
    { "driver": "ANF", "team": "Redbull Audi Sport", "points": 110 },
    { "driver": "Okami", "team": "Ampas Rally Team", "points": 102 },
    { "driver": "NVL", "team": "Just1 Racing", "points": 88 },
    { "driver": "Dipsi", "team": "Shinano Pertamina Team", "points": 85 },
    { "driver": "Kapak", "team": "Audi Redbull Sister Car", "points": 82 },
    { "driver": "Kevin", "team": "South Ranger Subaru", "points": 61 },
    { "driver": "M.Kevin", "team": "Redbull Audi Sport", "points": 59 },
    { "driver": "Naufal", "team": "Just1 Racing", "points": 49 },
    { "driver": "Douma", "team": "Porsche Rowe", "points": 47 },
    { "driver": "Fikri", "team": "Shinano Pertamina Team", "points": 47 },
    { "driver": "Kei", "team": "South Ranger Subaru", "points": 3 },
    { "driver": "Fadly", "team": "Shinano Pertamina Team", "points": 2 }
  ]
  